yace/__init__.py
yace/slang/__init__.py
yace/slang/cli.py
yace/slang/parser.py
yace/slang/ply/__init__.py
yace/slang/ply/lex.py
yace/slang/ply/yacc.py
yace/slang/ply/ygen.py
yace_sea_lang-0.1.2.dist-info/METADATA
yace_sea_lang-0.1.2.dist-info/WHEEL
yace_sea_lang-0.1.2.dist-info/entry_points.txt
yace_sea_lang-0.1.2.dist-info/top_level.txt
yace_sea_lang-0.1.2.dist-info/RECORD
