Metadata-Version: 2.1
Name: yace-sea-lang
Version: 0.1.2
Summary: The Sea Language -- An IDL for the C ABI and FFI interoperability
Home-page: https://github.com/safl/sea-lang
Author: Simon A. F. Lund
Author-email: os@safl.dk
Maintainer: Simon A. F. Lund
Maintainer-email: os@safl.dk
License: GPL-2.0
Classifier: Development Status :: 4 - Beta
Classifier: Environment :: Console
Classifier: Framework :: Pytest
Classifier: Intended Audience :: Developers
Classifier: Intended Audience :: System Administrators
Classifier: License :: OSI Approved :: GNU General Public License v2 (GPLv2)
Classifier: Programming Language :: Python
Classifier: Topic :: Software Development :: Testing
Classifier: Topic :: Software Development
Classifier: Topic :: Text Processing
Classifier: Topic :: Utilities
Requires-Dist: setuptools >=60
